{
  "meta": {
    "iconimage": "/assets/logo.svg",
    "font1": "Titan One",
    "showModals": false,
    "showContact": false,
    "showArchive": false,
    "showSearch": false,
    "showNav": true,
    "companyname": "Meme Genes",
    "siteUrl": "https://memegenes.com",
    "showDates": false,
    "twitterUsername": "toddlambert",
    "titleDefault": "MG Reports",
    "showSocial": true,
    "showNav2": false,
    "postcount": 12,
    "showPopup": false,
    "homecount": 8,
    "magicOptions": {
      "showMagic": true,
      "showMagicCat": false,
      "showMagicTag": true,
      "showMagicSearch": true
    },
    "titleTemplate": "%s",
    "showBranding": true,
    "title": "MG Reports",
    "showTitles": false,
    "showfooter": false,
    "image": "/assets/newspaper.webp",
    "showLegal": false,
    "description": "Do these memes make my butt look fat?",
    "icon512": "/assets/logo.svg",
    "showSwipe": true,
    "showConsent": false
  }
}